ojplay.py
outjack-19.dist-info/COPYING
outjack-19.dist-info/RECORD
outjack-19.dist-info/WHEEL
outjack-19.dist-info/top_level.txt
outjack-19.dist-info/METADATA
outjack-19.dist-info/entry_points.txt
outjack/cjack.cpython-312-i386-linux-gnu.so
outjack/ring.pxd
outjack/ring.pyxbld
outjack/portaudioclient.py
outjack/__init__.py
outjack/ring.pyx
outjack/portaudio.pxd
outjack/cjack.pyxbld
outjack/cjack.pyx
outjack/cportaudio.pyx
outjack/jackclient.py
outjack/cportaudio.cpython-312-i386-linux-gnu.so
outjack/jack.pxd
outjack/ring.cpython-312-i386-linux-gnu.so
outjack/cportaudio.pyxbld
