Metadata-Version: 2.1
Name: outjack
Version: 19
Summary: JACK and PortAudio integration for Python
Home-page: https://github.com/combatopera/outjack
Author: Andrzej Cichocki
Author-email: 3613868+combatopera@users.noreply.github.com
License-File: COPYING
Requires-Dist: Cython>=3.0.11
Requires-Dist: numpy>=2.0.2
Requires-Dist: pyrbo>=5
